{
   "type": "object",
   "definitions": {
      "ameliore_par_occupant": {
        "type": "object",
        "properties": {
          "kind": {
            "type": "string",
            "enum": [
              "Oui", "Non"
            ]
          }
          },
          "allOf": [
            {
              "if": {
                "properties": {
                  "kind": {
                    "const": "Oui"
                  }
                }
              },
              "then": {
                "properties": {
                  "payload": {
                    "type": "null",
                    "default": null
                  }
                }
              }
            },
            {
              "if": {
                "properties": {
                  "kind": {
                    "const": "Non"
                  }
                }
              },
              "then": {
                "properties": {
                  "payload": {
                    "type": "null",
                    "default": null
                  }
                }
              }
            }
          ]
        }
   ,
   "autre_personne_a_charge": {
     "type": "object",
     "properties": {
       "dateNaissance": {
         "type": "string",
         "format": "date"
       },
       "ressources": {
         "type": "number",
         "minimum": 0,
         "default": 0
       },
       "ascendantDescendantCollateralDeuxiemeTroisiemeDegre": {
         "type": "boolean",
         "default": false
       },
       "parente": {
         "$ref": "#/definitions/parente"
       },
       "incapacite80PourcentOuRestrictionEmploi": {
         "type": "boolean",
         "default": false
       },
       "beneficiaireL16119L3518L6433Secu": {
         "type": "boolean",
         "default": false
       },
       "titulaireAllocationPersonneAgee": {
         "type": "boolean",
         "default": false
       }
     }
   },
   "bailleur": {
     "type": "object",
     "properties": {
       "typeBailleur": {
         "$ref": "#/definitions/type_bailleur"
       },
       "respecteConventionTitreV": {
         "type": "boolean",
         "default": false
       },
       "respecteConventionTitreII": {
         "type": "boolean",
         "default": false
       },
       "construitAmelioreConditionsL83114": {
         "type": "boolean",
         "default": false
       },
       "acquisitionAidesEtatPretTitreIIOuLivreIII": {
         "type": "boolean",
         "default": false
       }
     }
   },
   "categorie_equivalence_loyer_allocation_logement_foyer": {
     "type": "object",
     "properties": {
       "kind": {
         "type": "string",
         "enum": [
           "EtudiantLogeEnChambre", "EtudiantLogeEnChambreRehabilitee",
           "PersonnesAgeesSelon3DeD842_16", "AutresPersonnes"
         ]
       }
       },
       "allOf": [
         {
           "if": {
             "properties": {
               "kind": {
                 "const": "EtudiantLogeEnChambre"
               }
             }
           },
           "then": {
             "properties": {
               "payload": {
                 "type": "null",
                 "default": null
               }
             }
           }
         },
         {
           "if": {
             "properties": {
               "kind": {
                 "const": "EtudiantLogeEnChambreRehabilitee"
               }
             }
           },
           "then": {
             "properties": {
               "payload": {
                 "type": "null",
                 "default": null
               }
             }
           }
         },
         {
           "if": {
             "properties": {
               "kind": {
                 "const": "PersonnesAgeesSelon3DeD842_16"
               }
             }
           },
           "then": {
             "properties": {
               "payload": {
                 "type": "null",
                 "default": null
               }
             }
           }
         },
         {
           "if": {
             "properties": {
               "kind": {
                 "const": "AutresPersonnes"
               }
             }
           },
           "then": {
             "properties": {
               "payload": {
                 "type": "null",
                 "default": null
               }
             }
           }
         }
       ]
     }
,
"changement_logement_d842_4": {
  "type": "object",
  "properties": {
    "kind": {
      "type": "string",
      "enum": [
        "Changement", "PasDeChangement"
      ]
    }
    },
    "allOf": [
      {
        "if": {
          "properties": {
            "kind": {
              "const": "Changement"
            }
          }
        },
        "then": {
          "properties": {
            "payload": {
              "$ref": "#/definitions/infos_changement_logement_d842_4"
            }
          }
        }
      },
      {
        "if": {
          "properties": {
            "kind": {
              "const": "PasDeChangement"
            }
          }
        },
        "then": {
          "properties": {
            "payload": {
              "type": "null",
              "default": null
            }
          }
        }
      }
    ]
  }
,
"date_de_naissance_ou_mois_de_grossesse": {
  "type": "object",
  "properties": {
    "kind": {
      "type": "string",
      "enum": [
        "DateDeNaissance",
        "AvantPremierJourMoisCivilTroisiemeMoisDeGrossesse",
        "ApresPremierJourMoisCivilTroisiemeMoisDeGrossesse"
      ]
    }
    },
    "allOf": [
      {
        "if": {
          "properties": {
            "kind": {
              "const": "DateDeNaissance"
            }
          }
        },
        "then": {
          "properties": {
            "payload": {
              "type": "string",
              "format": "date"
            }
          }
        }
      },
      {
        "if": {
          "properties": {
            "kind": {
              "const": "AvantPremierJourMoisCivilTroisiemeMoisDeGrossesse"
            }
          }
        },
        "then": {
          "properties": {
            "payload": {
              "type": "null",
              "default": null
            }
          }
        }
      },
      {
        "if": {
          "properties": {
            "kind": {
              "const": "ApresPremierJourMoisCivilTroisiemeMoisDeGrossesse"
            }
          }
        },
        "then": {
          "properties": {
            "payload": {
              "type": "null",
              "default": null
            }
          }
        }
      }
    ]
  }
,
"date_naissance_troisieme_ou_dernier_plus_enfant": {
  "type": "object",
  "properties": {
    "kind": {
      "type": "string",
      "enum": [
        "MoinsDeTroisEnfants", "PlusDeTroisEnfants"
      ]
    }
    },
    "allOf": [
      {
        "if": {
          "properties": {
            "kind": {
              "const": "MoinsDeTroisEnfants"
            }
          }
        },
        "then": {
          "properties": {
            "payload": {
              "type": "null",
              "default": null
            }
          }
        }
      },
      {
        "if": {
          "properties": {
            "kind": {
              "const": "PlusDeTroisEnfants"
            }
          }
        },
        "then": {
          "properties": {
            "payload": {
              "$ref": "#/definitions/date_de_naissance_ou_mois_de_grossesse"
            }
          }
        }
      }
    ]
  }
,
"demandeur": {
  "type": "object",
  "properties": {
    "satisfaitConditionsL5122CodeSecuriteSociale": {
      "type": "boolean",
      "default": false
    },
    "ageDemandeur": {
      "type": "number",
      "default": 0
    },
    "dateNaissance": {
      "type": "string",
      "format": "date"
    },
    "contratDeTravail": {
      "$ref": "#/definitions/type_contrat_travail"
    },
    "nationalite": {
      "$ref": "#/definitions/nationalite"
    },
    "patrimoine": {
      "$ref": "#/definitions/patrimoine"
    },
    "personneHebergeeCentreSoinLL162223SecuriteSociale": {
      "type": "boolean",
      "default": false
    }
  }
},
"enfant_a_charge": {
  "type": "object",
  "properties": {
    "identifiant": {
      "type": "number",
      "default": 0
    },
    "beneficieTitrePersonnelAidePersonnelleLogement": {
      "type": "boolean",
      "default": false
    },
    "aDejaOuvertDroitAuxAllocationsFamiliales": {
      "type": "boolean",
      "default": false
    },
    "dateDeNaissance": {
      "type": "string",
      "format": "date"
    },
    "remunerationMensuelle": {
      "type": "number",
      "minimum": 0,
      "default": 0
    },
    "obligationScolaire": {
      "$ref": "#/definitions/situation_obligation_scolaire"
    },
    "priseEnCharge": {
      "$ref": "#/definitions/prise_en_charge"
    },
    "age": {
      "type": "number",
      "default": 0
    },
    "situationGardeAlternee": {
      "$ref": "#/definitions/situation_garde_alternee"
    }
  }
},
"informations_calcul_a_p_l": {
  "type": "object",
  "properties": {
    "kind": {
      "type": "string",
      "enum": [
        "InfosLocatif", "InfosLogementFoyer", "InfosAccessionPropriete"
      ]
    }
    },
    "allOf": [
      {
        "if": {
          "properties": {
            "kind": {
              "const": "InfosLocatif"
            }
          }
        },
        "then": {
          "properties": {
            "payload": {
              "$ref": "#/definitions/informations_calcul_a_p_l_locatif"
            }
          }
        }
      },
      {
        "if": {
          "properties": {
            "kind": {
              "const": "InfosLogementFoyer"
            }
          }
        },
        "then": {
          "properties": {
            "payload": {
              "$ref": "#/definitions/informations_calcul_a_p_l_logement_foyer"
            }
          }
        }
      },
      {
        "if": {
          "properties": {
            "kind": {
              "const": "InfosAccessionPropriete"
            }
          }
        },
        "then": {
          "properties": {
            "payload": {
              "$ref": "#/definitions/informations_calcul_a_p_l_accession_propriete"
            }
          }
        }
      }
    ]
  }
,
"informations_calcul_a_p_l_accession_propriete": {
  "type": "object",
  "properties": {
    "mensualitePrincipale": {
      "type": "number",
      "minimum": 0,
      "default": 0
    },
    "chargesMensuellesPret": {
      "type": "number",
      "minimum": 0,
      "default": 0
    },
    "dateSignaturePret": {
      "type": "string",
      "format": "date"
    },
    "dateEntreeLogement": {
      "type": "string",
      "format": "date"
    },
    "typeTravauxLogementD83215": {
      "$ref": "#/definitions/type_travaux_logement_d832_15"
    },
    "typeTravauxLogementR8425": {
      "$ref": "#/definitions/type_travaux_logement_r842_5"
    },
    "localHabitePremiereFoisBeneficiaire": {
      "type": "boolean",
      "default": false
    },
    "copropriete": {
      "type": "boolean",
      "default": false
    },
    "situationR822111317": {
      "type": "boolean",
      "default": false
    },
    "typePret": {
      "$ref": "#/definitions/type_pret"
    },
    "ancienneteLogement": {
      "$ref": "#/definitions/neuf_ou_ancien"
    }
  }
},
"informations_calcul_a_p_l_locatif": {
  "type": "object",
  "properties": {
    "loyerPrincipal": {
      "type": "number",
      "minimum": 0,
      "default": 0
    },
    "beneficiaireAideAdulteOuEnfantHandicapes": {
      "type": "boolean",
      "default": false
    },
    "logementEstChambre": {
      "type": "boolean",
      "default": false
    },
    "colocation": {
      "type": "boolean",
      "default": false
    },
    "ageesOuHandicapAdultesHebergeesOnereuxParticuliers": {
      "type": "boolean",
      "default": false
    },
    "reductionLoyerSolidarite": {
      "type": "number",
      "minimum": 0,
      "default": 0
    },
    "logementMeubleD8422": {
      "type": "boolean",
      "default": false
    },
    "changementLogementD8424": {
      "$ref": "#/definitions/changement_logement_d842_4"
    }
  }
},
"informations_calcul_a_p_l_logement_foyer": {
  "type": "object",
  "properties": {
    "redevance": {
      "type": "number",
      "minimum": 0,
      "default": 0
    },
    "categorieEquivalenceLoyerD84216": {
      "$ref": "#/definitions/categorie_equivalence_loyer_allocation_logement_foyer"
    }
  }
},
"infos_changement_logement_d842_4": {
  "type": "object",
  "properties": {
    "ancienLoyerPrincipal": {
      "type": "number",
      "minimum": 0,
      "default": 0
    },
    "ancienneAllocationLogement": {
      "type": "number",
      "minimum": 0,
      "default": 0
    }
  }
},
"location": {
  "type": "object",
  "properties": {
    "bailleur": {
      "$ref": "#/definitions/bailleur"
    }
  }
},
"logement": {
  "type": "object",
  "properties": {
    "residencePrincipale": {
      "type": "boolean",
      "default": false
    },
    "estEhpadOuMaisonAutonomieL31312Asf": {
      "type": "boolean",
      "default": false
    },
    "modeOccupation": {
      "$ref": "#/definitions/mode_occupation"
    },
    "proprietaire": {
      "$ref": "#/definitions/parent_ou_autre"
    },
    "loueOuSousLoueADesTiers": {
      "$ref": "#/definitions/loue_ou_sous_loue_a_des_tiers"
    },
    "usufruit": {
      "$ref": "#/definitions/parent_ou_autre"
    },
    "logementDecentL89462": {
      "type": "boolean",
      "default": false
    },
    "loyersL8233": {
      "type": "number",
      "minimum": 0,
      "default": 0
    },
    "surfaceMCarres": {
      "type": "number",
      "default": 0
    },
    "estAncienL8312": {
      "type": "boolean",
      "default": false
    },
    "situeCommuneDesequilibreL8312": {
      "type": "boolean",
      "default": false
    },
    "zone": {
      "$ref": "#/definitions/zone_d_habitation"
    }
  }
},
"logement_foyer": {
  "type": "object",
  "properties": {
    "typeUser": {
      "$ref": "#/definitions/type_logement_foyer"
    },
    "dateConventionnement": {
      "type": "string",
      "format": "date"
    },
    "location": {
      "$ref": "#/definitions/location"
    },
    "remplitConditionsR83221": {
      "type": "boolean",
      "default": false
    },
    "construitApplicationLoi195712III": {
      "type": "boolean",
      "default": false
    }
  }
},
"loue_ou_sous_loue_a_des_tiers": {
  "type": "object",
  "properties": {
    "kind": {
      "type": "string",
      "enum": [
        "Non", "Oui"
      ]
    }
    },
    "allOf": [
      {
        "if": {
          "properties": {
            "kind": {
              "const": "Non"
            }
          }
        },
        "then": {
          "properties": {
            "payload": {
              "type": "null",
              "default": null
            }
          }
        }
      },
      {
        "if": {
          "properties": {
            "kind": {
              "const": "Oui"
            }
          }
        },
        "then": {
          "properties": {
            "payload": {
              "$ref": "#/definitions/personne_sous_location"
            }
          }
        }
      }
    ]
  }
,
"menage": {
  "type": "object",
  "properties": {
    "prestationsRecues": {
      "type": "array",
      "default": [],
      "items": {
        "$ref": "#/definitions/prestation_recue"
      }
    },
    "logement": {
      "$ref": "#/definitions/logement"
    },
    "personnesACharge": {
      "type": "array",
      "default": [],
      "items": {
        "$ref": "#/definitions/personne_a_charge"
      }
    },
    "nombreAutresOccupantsLogement": {
      "type": "number",
      "default": 0
    },
    "situationFamiliale": {
      "$ref": "#/definitions/situation_familiale"
    },
    "conditionRattacheFoyerFiscalParentIfi": {
      "type": "boolean",
      "default": false
    },
    "nombreEnfantsANaitreApresTroisiemeMoisGrossesse": {
      "type": "number",
      "default": 0
    },
    "enfantANaitreApresQuatriemeMoisGrossesse": {
      "type": "boolean",
      "default": false
    },
    "dateNaissanceTroisiemeEnfantOuDernierSiPlus": {
      "$ref": "#/definitions/date_naissance_troisieme_ou_dernier_plus_enfant"
    }
  }
},
"mode_occupation": {
  "type": "object",
  "properties": {
    "kind": {
      "type": "string",
      "enum": [
        "Locataire", "ResidentLogementFoyer",
        "AccessionProprieteLocalUsageExclusifHabitation", "SousLocataire",
        "LocationAccession"
      ]
    }
    },
    "allOf": [
      {
        "if": {
          "properties": {
            "kind": {
              "const": "Locataire"
            }
          }
        },
        "then": {
          "properties": {
            "payload": {
              "$ref": "#/definitions/location"
            }
          }
        }
      },
      {
        "if": {
          "properties": {
            "kind": {
              "const": "ResidentLogementFoyer"
            }
          }
        },
        "then": {
          "properties": {
            "payload": {
              "$ref": "#/definitions/logement_foyer"
            }
          }
        }
      },
      {
        "if": {
          "properties": {
            "kind": {
              "const": "AccessionProprieteLocalUsageExclusifHabitation"
            }
          }
        },
        "then": {
          "properties": {
            "payload": {
              "$ref": "#/definitions/proprietaire"
            }
          }
        }
      },
      {
        "if": {
          "properties": {
            "kind": {
              "const": "SousLocataire"
            }
          }
        },
        "then": {
          "properties": {
            "payload": {
              "$ref": "#/definitions/location"
            }
          }
        }
      },
      {
        "if": {
          "properties": {
            "kind": {
              "const": "LocationAccession"
            }
          }
        },
        "then": {
          "properties": {
            "payload": {
              "$ref": "#/definitions/proprietaire"
            }
          }
        }
      }
    ]
  }
,
"nationalite": {
  "type": "object",
  "properties": {
    "kind": {
      "type": "string",
      "enum": [
        "Francaise", "Etrangere"
      ]
    }
    },
    "allOf": [
      {
        "if": {
          "properties": {
            "kind": {
              "const": "Francaise"
            }
          }
        },
        "then": {
          "properties": {
            "payload": {
              "type": "null",
              "default": null
            }
          }
        }
      },
      {
        "if": {
          "properties": {
            "kind": {
              "const": "Etrangere"
            }
          }
        },
        "then": {
          "properties": {
            "payload": {
              "type": "null",
              "default": null
            }
          }
        }
      }
    ]
  }
,
"neuf_ou_ancien": {
  "type": "object",
  "properties": {
    "kind": {
      "type": "string",
      "enum": [
        "Neuf", "Ancien"
      ]
    }
    },
    "allOf": [
      {
        "if": {
          "properties": {
            "kind": {
              "const": "Neuf"
            }
          }
        },
        "then": {
          "properties": {
            "payload": {
              "type": "null",
              "default": null
            }
          }
        }
      },
      {
        "if": {
          "properties": {
            "kind": {
              "const": "Ancien"
            }
          }
        },
        "then": {
          "properties": {
            "payload": {
              "$ref": "#/definitions/ameliore_par_occupant"
            }
          }
        }
      }
    ]
  }
,
"parent_ou_autre": {
  "type": "object",
  "properties": {
    "kind": {
      "type": "string",
      "enum": [
        "DemandeurOuConjointOuParentOuViaPartsSocietes", "Autre"
      ]
    }
    },
    "allOf": [
      {
        "if": {
          "properties": {
            "kind": {
              "const": "DemandeurOuConjointOuParentOuViaPartsSocietes"
            }
          }
        },
        "then": {
          "properties": {
            "payload": {
              "type": "number",
              "default": 0
            }
          }
        }
      },
      {
        "if": {
          "properties": {
            "kind": {
              "const": "Autre"
            }
          }
        },
        "then": {
          "properties": {
            "payload": {
              "type": "null",
              "default": null
            }
          }
        }
      }
    ]
  }
,
"parente": {
  "type": "object",
  "properties": {
    "kind": {
      "type": "string",
      "enum": [
        "Ascendant", "Descendant", "CollateralDeuxiemeTroisiemeDegre"
      ]
    }
    },
    "allOf": [
      {
        "if": {
          "properties": {
            "kind": {
              "const": "Ascendant"
            }
          }
        },
        "then": {
          "properties": {
            "payload": {
              "type": "null",
              "default": null
            }
          }
        }
      },
      {
        "if": {
          "properties": {
            "kind": {
              "const": "Descendant"
            }
          }
        },
        "then": {
          "properties": {
            "payload": {
              "type": "null",
              "default": null
            }
          }
        }
      },
      {
        "if": {
          "properties": {
            "kind": {
              "const": "CollateralDeuxiemeTroisiemeDegre"
            }
          }
        },
        "then": {
          "properties": {
            "payload": {
              "type": "null",
              "default": null
            }
          }
        }
      }
    ]
  }
,
"patrimoine": {
  "type": "object",
  "properties": {
    "produisantRevenuPeriodeR82233R8224": {
      "type": "number",
      "minimum": 0,
      "default": 0
    },
    "neProduisantPasRevenuPeriodeR82233R8224": {
      "type": "number",
      "minimum": 0,
      "default": 0
    }
  }
},
"personne_a_charge": {
  "type": "object",
  "properties": {
    "kind": {
      "type": "string",
      "enum": [
        "EnfantACharge", "AutrePersonneACharge"
      ]
    }
    },
    "allOf": [
      {
        "if": {
          "properties": {
            "kind": {
              "const": "EnfantACharge"
            }
          }
        },
        "then": {
          "properties": {
            "payload": {
              "$ref": "#/definitions/enfant_a_charge"
            }
          }
        }
      },
      {
        "if": {
          "properties": {
            "kind": {
              "const": "AutrePersonneACharge"
            }
          }
        },
        "then": {
          "properties": {
            "payload": {
              "$ref": "#/definitions/autre_personne_a_charge"
            }
          }
        }
      }
    ]
  }
,
"personne_sous_location": {
  "type": "object",
  "properties": {
    "agePersonneSousLocation": {
      "type": "number",
      "default": 0
    },
    "conformeArticleL4421": {
      "type": "boolean",
      "default": false
    }
  }
},
"prestation_recue": {
  "type": "object",
  "properties": {
    "kind": {
      "type": "string",
      "enum": [
        "AllocationsFamiliales", "ComplementFamilial",
        "AllocationJeuneEnfant", "AllocationSoutienFamilial",
        "AllocationSoutienEnfantHandicape", "AllocationAdulteHandicape"
      ]
    }
    },
    "allOf": [
      {
        "if": {
          "properties": {
            "kind": {
              "const": "AllocationsFamiliales"
            }
          }
        },
        "then": {
          "properties": {
            "payload": {
              "type": "null",
              "default": null
            }
          }
        }
      },
      {
        "if": {
          "properties": {
            "kind": {
              "const": "ComplementFamilial"
            }
          }
        },
        "then": {
          "properties": {
            "payload": {
              "type": "null",
              "default": null
            }
          }
        }
      },
      {
        "if": {
          "properties": {
            "kind": {
              "const": "AllocationJeuneEnfant"
            }
          }
        },
        "then": {
          "properties": {
            "payload": {
              "type": "null",
              "default": null
            }
          }
        }
      },
      {
        "if": {
          "properties": {
            "kind": {
              "const": "AllocationSoutienFamilial"
            }
          }
        },
        "then": {
          "properties": {
            "payload": {
              "type": "null",
              "default": null
            }
          }
        }
      },
      {
        "if": {
          "properties": {
            "kind": {
              "const": "AllocationSoutienEnfantHandicape"
            }
          }
        },
        "then": {
          "properties": {
            "payload": {
              "type": "null",
              "default": null
            }
          }
        }
      },
      {
        "if": {
          "properties": {
            "kind": {
              "const": "AllocationAdulteHandicape"
            }
          }
        },
        "then": {
          "properties": {
            "payload": {
              "type": "null",
              "default": null
            }
          }
        }
      }
    ]
  }
,
"pret": {
  "type": "object",
  "properties": {
    "typePret": {
      "$ref": "#/definitions/type_pret"
    },
    "dateSignature": {
      "type": "string",
      "format": "date"
    },
    "titulairePret": {
      "$ref": "#/definitions/titulaire_pret"
    }
  }
},
"prise_en_charge": {
  "type": "object",
  "properties": {
    "kind": {
      "type": "string",
      "enum": [
        "EffectiveEtPermanente", "ResidenceAlterneeAllocataireUnique",
        "ResidenceAlterneeAllocationsPartagee"
      ]
    }
    },
    "allOf": [
      {
        "if": {
          "properties": {
            "kind": {
              "const": "EffectiveEtPermanente"
            }
          }
        },
        "then": {
          "properties": {
            "payload": {
              "type": "null",
              "default": null
            }
          }
        }
      },
      {
        "if": {
          "properties": {
            "kind": {
              "const": "ResidenceAlterneeAllocataireUnique"
            }
          }
        },
        "then": {
          "properties": {
            "payload": {
              "type": "null",
              "default": null
            }
          }
        }
      },
      {
        "if": {
          "properties": {
            "kind": {
              "const": "ResidenceAlterneeAllocationsPartagee"
            }
          }
        },
        "then": {
          "properties": {
            "payload": {
              "type": "null",
              "default": null
            }
          }
        }
      }
    ]
  }
,
"proprietaire": {
  "type": "object",
  "properties": {
    "pret": {
      "$ref": "#/definitions/pret"
    }
  }
},
"situation_familiale": {
  "type": "object",
  "properties": {
    "kind": {
      "type": "string",
      "enum": [
        "Celibataire", "Maries", "Pacses", "Concubins",
        "CelibataireSepareDeFait", "ConcubinageDontSepareDeFait"
      ]
    }
    },
    "allOf": [
      {
        "if": {
          "properties": {
            "kind": {
              "const": "Celibataire"
            }
          }
        },
        "then": {
          "properties": {
            "payload": {
              "type": "null",
              "default": null
            }
          }
        }
      },
      {
        "if": {
          "properties": {
            "kind": {
              "const": "Maries"
            }
          }
        },
        "then": {
          "properties": {
            "payload": {
              "type": "string",
              "format": "date"
            }
          }
        }
      },
      {
        "if": {
          "properties": {
            "kind": {
              "const": "Pacses"
            }
          }
        },
        "then": {
          "properties": {
            "payload": {
              "type": "null",
              "default": null
            }
          }
        }
      },
      {
        "if": {
          "properties": {
            "kind": {
              "const": "Concubins"
            }
          }
        },
        "then": {
          "properties": {
            "payload": {
              "type": "null",
              "default": null
            }
          }
        }
      },
      {
        "if": {
          "properties": {
            "kind": {
              "const": "CelibataireSepareDeFait"
            }
          }
        },
        "then": {
          "properties": {
            "payload": {
              "type": "null",
              "default": null
            }
          }
        }
      },
      {
        "if": {
          "properties": {
            "kind": {
              "const": "ConcubinageDontSepareDeFait"
            }
          }
        },
        "then": {
          "properties": {
            "payload": {
              "type": "null",
              "default": null
            }
          }
        }
      }
    ]
  }
,
"situation_garde_alternee": {
  "type": "object",
  "properties": {
    "kind": {
      "type": "string",
      "enum": [
        "PasDeGardeAlternee", "GardeAlterneeCoefficientPriseEnCharge"
      ]
    }
    },
    "allOf": [
      {
        "if": {
          "properties": {
            "kind": {
              "const": "PasDeGardeAlternee"
            }
          }
        },
        "then": {
          "properties": {
            "payload": {
              "type": "null",
              "default": null
            }
          }
        }
      },
      {
        "if": {
          "properties": {
            "kind": {
              "const": "GardeAlterneeCoefficientPriseEnCharge"
            }
          }
        },
        "then": {
          "properties": {
            "payload": {
              "type": "number",
              "default": 0
            }
          }
        }
      }
    ]
  }
,
"situation_obligation_scolaire": {
  "type": "object",
  "properties": {
    "kind": {
      "type": "string",
      "enum": [
        "Avant", "Pendant", "Apres"
      ]
    }
    },
    "allOf": [
      {
        "if": {
          "properties": {
            "kind": {
              "const": "Avant"
            }
          }
        },
        "then": {
          "properties": {
            "payload": {
              "type": "null",
              "default": null
            }
          }
        }
      },
      {
        "if": {
          "properties": {
            "kind": {
              "const": "Pendant"
            }
          }
        },
        "then": {
          "properties": {
            "payload": {
              "type": "null",
              "default": null
            }
          }
        }
      },
      {
        "if": {
          "properties": {
            "kind": {
              "const": "Apres"
            }
          }
        },
        "then": {
          "properties": {
            "payload": {
              "type": "null",
              "default": null
            }
          }
        }
      }
    ]
  }
,
"titulaire_pret": {
  "type": "object",
  "properties": {
    "kind": {
      "type": "string",
      "enum": [
        "Demandeur", "VendeurQuandDemandeurAContratLocationAccession"
      ]
    }
    },
    "allOf": [
      {
        "if": {
          "properties": {
            "kind": {
              "const": "Demandeur"
            }
          }
        },
        "then": {
          "properties": {
            "payload": {
              "type": "null",
              "default": null
            }
          }
        }
      },
      {
        "if": {
          "properties": {
            "kind": {
              "const": "VendeurQuandDemandeurAContratLocationAccession"
            }
          }
        },
        "then": {
          "properties": {
            "payload": {
              "type": "null",
              "default": null
            }
          }
        }
      }
    ]
  }
,
"type_bailleur": {
  "type": "object",
  "properties": {
    "kind": {
      "type": "string",
      "enum": [
        "BailleurSocial", "BailleurPrive"
      ]
    }
    },
    "allOf": [
      {
        "if": {
          "properties": {
            "kind": {
              "const": "BailleurSocial"
            }
          }
        },
        "then": {
          "properties": {
            "payload": {
              "type": "null",
              "default": null
            }
          }
        }
      },
      {
        "if": {
          "properties": {
            "kind": {
              "const": "BailleurPrive"
            }
          }
        },
        "then": {
          "properties": {
            "payload": {
              "type": "null",
              "default": null
            }
          }
        }
      }
    ]
  }
,
"type_contrat_travail": {
  "type": "object",
  "properties": {
    "kind": {
      "type": "string",
      "enum": [
        "CDI", "Autres"
      ]
    }
    },
    "allOf": [
      {
        "if": {
          "properties": {
            "kind": {
              "const": "CDI"
            }
          }
        },
        "then": {
          "properties": {
            "payload": {
              "type": "null",
              "default": null
            }
          }
        }
      },
      {
        "if": {
          "properties": {
            "kind": {
              "const": "Autres"
            }
          }
        },
        "then": {
          "properties": {
            "payload": {
              "type": "null",
              "default": null
            }
          }
        }
      }
    ]
  }
,
"type_logement_foyer": {
  "type": "object",
  "properties": {
    "kind": {
      "type": "string",
      "enum": [
        "LogementPersonnesAgeesOuHandicapees", "ResidenceSociale",
        "FoyerJeunesTrvailleursOuMigrantsConventionneL353_2Avant1995",
        "Autre"
      ]
    }
    },
    "allOf": [
      {
        "if": {
          "properties": {
            "kind": {
              "const": "LogementPersonnesAgeesOuHandicapees"
            }
          }
        },
        "then": {
          "properties": {
            "payload": {
              "type": "null",
              "default": null
            }
          }
        }
      },
      {
        "if": {
          "properties": {
            "kind": {
              "const": "ResidenceSociale"
            }
          }
        },
        "then": {
          "properties": {
            "payload": {
              "type": "null",
              "default": null
            }
          }
        }
      },
      {
        "if": {
          "properties": {
            "kind": {
              "const": "FoyerJeunesTrvailleursOuMigrantsConventionneL353_2Avant1995"
            }
          }
        },
        "then": {
          "properties": {
            "payload": {
              "type": "null",
              "default": null
            }
          }
        }
      },
      {
        "if": {
          "properties": {
            "kind": {
              "const": "Autre"
            }
          }
        },
        "then": {
          "properties": {
            "payload": {
              "type": "null",
              "default": null
            }
          }
        }
      }
    ]
  }
,
"type_pret": {
  "type": "object",
  "properties": {
    "kind": {
      "type": "string",
      "enum": [
        "D331_32", "D331_63_64", "D331_59_8", "D331_76_1", "Autre"
      ]
    }
    },
    "allOf": [
      {
        "if": {
          "properties": {
            "kind": {
              "const": "D331_32"
            }
          }
        },
        "then": {
          "properties": {
            "payload": {
              "type": "null",
              "default": null
            }
          }
        }
      },
      {
        "if": {
          "properties": {
            "kind": {
              "const": "D331_63_64"
            }
          }
        },
        "then": {
          "properties": {
            "payload": {
              "type": "null",
              "default": null
            }
          }
        }
      },
      {
        "if": {
          "properties": {
            "kind": {
              "const": "D331_59_8"
            }
          }
        },
        "then": {
          "properties": {
            "payload": {
              "type": "null",
              "default": null
            }
          }
        }
      },
      {
        "if": {
          "properties": {
            "kind": {
              "const": "D331_76_1"
            }
          }
        },
        "then": {
          "properties": {
            "payload": {
              "type": "null",
              "default": null
            }
          }
        }
      },
      {
        "if": {
          "properties": {
            "kind": {
              "const": "Autre"
            }
          }
        },
        "then": {
          "properties": {
            "payload": {
              "type": "null",
              "default": null
            }
          }
        }
      }
    ]
  }
,
"type_travaux_logement_d832_15": {
  "type": "object",
  "properties": {
    "kind": {
      "type": "string",
      "enum": [
        "TravauxPourAcquisitionD832_15_1",
        "TravauxSurLogementDejaAcquisD832_15_2", "PasDeTravaux"
      ]
    }
    },
    "allOf": [
      {
        "if": {
          "properties": {
            "kind": {
              "const": "TravauxPourAcquisitionD832_15_1"
            }
          }
        },
        "then": {
          "properties": {
            "payload": {
              "type": "null",
              "default": null
            }
          }
        }
      },
      {
        "if": {
          "properties": {
            "kind": {
              "const": "TravauxSurLogementDejaAcquisD832_15_2"
            }
          }
        },
        "then": {
          "properties": {
            "payload": {
              "type": "null",
              "default": null
            }
          }
        }
      },
      {
        "if": {
          "properties": {
            "kind": {
              "const": "PasDeTravaux"
            }
          }
        },
        "then": {
          "properties": {
            "payload": {
              "type": "null",
              "default": null
            }
          }
        }
      }
    ]
  }
,
"type_travaux_logement_r842_5": {
  "type": "object",
  "properties": {
    "kind": {
      "type": "string",
      "enum": [
        "ObjectifDecenceLogement", "PrevuDansListeR321_15",
        "AgrandirOuRendreHabitableD331_63", "PasDeTravaux"
      ]
    }
    },
    "allOf": [
      {
        "if": {
          "properties": {
            "kind": {
              "const": "ObjectifDecenceLogement"
            }
          }
        },
        "then": {
          "properties": {
            "payload": {
              "type": "null",
              "default": null
            }
          }
        }
      },
      {
        "if": {
          "properties": {
            "kind": {
              "const": "PrevuDansListeR321_15"
            }
          }
        },
        "then": {
          "properties": {
            "payload": {
              "type": "null",
              "default": null
            }
          }
        }
      },
      {
        "if": {
          "properties": {
            "kind": {
              "const": "AgrandirOuRendreHabitableD331_63"
            }
          }
        },
        "then": {
          "properties": {
            "payload": {
              "type": "null",
              "default": null
            }
          }
        }
      },
      {
        "if": {
          "properties": {
            "kind": {
              "const": "PasDeTravaux"
            }
          }
        },
        "then": {
          "properties": {
            "payload": {
              "type": "null",
              "default": null
            }
          }
        }
      }
    ]
  }
,
"zone_d_habitation": {
  "type": "object",
  "properties": {
    "kind": {
      "type": "string",
      "enum": [
        "Zone1", "Zone2", "Zone3"
      ]
    }
    },
    "allOf": [
      {
        "if": {
          "properties": {
            "kind": {
              "const": "Zone1"
            }
          }
        },
        "then": {
          "properties": {
            "payload": {
              "type": "null",
              "default": null
            }
          }
        }
      },
      {
        "if": {
          "properties": {
            "kind": {
              "const": "Zone2"
            }
          }
        },
        "then": {
          "properties": {
            "payload": {
              "type": "null",
              "default": null
            }
          }
        }
      },
      {
        "if": {
          "properties": {
            "kind": {
              "const": "Zone3"
            }
          }
        },
        "then": {
          "properties": {
            "payload": {
              "type": "null",
              "default": null
            }
          }
        }
      }
    ]
  }

},
"properties": {
   "menageIn": {
     "$ref": "#/definitions/menage"
   },
   "demandeurIn": {
     "$ref": "#/definitions/demandeur"
   },
   "informationsCalculIn": {
     "$ref": "#/definitions/informations_calcul_a_p_l"
   },
   "dateCouranteIn": {
     "type": "string",
     "format": "date"
   },
   "ressourcesMenagePrisesEnCompteIn": {
     "type": "number",
     "minimum": 0,
     "default": 0
   }
}
}